numgrids/__init__.py
numgrids/api.py
numgrids/axes.py
numgrids/diff.py
numgrids/grids.py
numgrids/integration.py
numgrids/interpol.py
numgrids/plots.py
numgrids/utils.py
numgrids-0.3.0.dist-info/LICENSE
numgrids-0.3.0.dist-info/METADATA
numgrids-0.3.0.dist-info/WHEEL
numgrids-0.3.0.dist-info/top_level.txt
numgrids-0.3.0.dist-info/RECORD
