Metadata-Version: 2.1
Name: numgrids
Version: 0.3.0
Summary: Working with numerical grids made easy.
Home-page: https://github.com/maroba/numgrids
Author: Matthias Baer
Author-email: matthias.r.baer@googlemail.com
License: MIT
Platform: ALL
Classifier: Operating System :: OS Independent
Classifier: Programming Language :: Python :: 3
Requires-Python: >=3.8
License-File: LICENSE
Requires-Dist: numpy
Requires-Dist: scipy (>=1.10.1)
Requires-Dist: matplotlib
Requires-Dist: findiff
